<?xml version='1.0' encoding='UTF-8' standalone='yes'?>
<tomtom version="4.12.0" release="Tue Jun 27 16:22:50 2017 -0700">
  <model>
    <command_line>tomtom -verbosity 1 -oc meme_tomtom_out -min-overlap 5 -dist pearson -evalue -thresh 1 -no-ssc -bfile ./background meme_out/meme.xml db/EUKARYOTE/jolma2013.meme db/JASPAR/JASPAR2018_CORE_vertebrates_non-redundant.meme db/MOUSE/uniprobe_mouse.meme</command_line>
    <distance_measure value="pearson"/>
    <threshold type="evalue">1</threshold>
    <alphabet name="DNA" like="dna">
      <letter id="A" symbol="A" complement="T" name="Adenine" colour="CC0000"/>
      <letter id="C" symbol="C" complement="G" name="Cytosine" colour="0000CC"/>
      <letter id="G" symbol="G" complement="C" name="Guanine" colour="FFB300"/>
      <letter id="T" symbol="T" aliases="U" complement="A" name="Thymine" colour="008000"/>
      <letter id="N" symbol="N" aliases="X." equals="ACGT" name="Any base"/>
      <letter id="V" symbol="V" equals="ACG" name="Not T"/>
      <letter id="H" symbol="H" equals="ACT" name="Not G"/>
      <letter id="D" symbol="D" equals="AGT" name="Not C"/>
      <letter id="B" symbol="B" equals="CGT" name="Not A"/>
      <letter id="M" symbol="M" equals="AC" name="Amino"/>
      <letter id="R" symbol="R" equals="AG" name="Purine"/>
      <letter id="W" symbol="W" equals="AT" name="Weak"/>
      <letter id="S" symbol="S" equals="CG" name="Strong"/>
      <letter id="Y" symbol="Y" equals="CT" name="Pyrimidine"/>
      <letter id="K" symbol="K" equals="GT" name="Keto"/>
    </alphabet>
    <strands>both</strands>
    <background from="file" A="0.2302" C="0.2698" G="0.2698" T="0.2302" file="./background"/>
    <host>node250</host>
    <when>Sun May 13 23:10:44 2018</when>
  </model>
  <query_dbs>
    <db source="meme_out/meme.xml" name="meme" loaded="3" excluded="0" last_mod_date="Sun May 13 21:52:00 2018"/>
  </query_dbs>
  <target_dbs>
    <db source="db/EUKARYOTE/jolma2013.meme" name="jolma2013" loaded="843" excluded="0" last_mod_date="Thu Dec  7 02:58:49 2017"/>
    <db source="db/JASPAR/JASPAR2018_CORE_vertebrates_non-redundant.meme" name="JASPAR2018 CORE vertebrates non-redundant" loaded="579" excluded="0" last_mod_date="Thu Dec  7 19:38:42 2017"/>
    <db source="db/MOUSE/uniprobe_mouse.meme" name="uniprobe mouse" loaded="386" excluded="0" last_mod_date="Thu Dec  7 02:59:31 2017"/>
  </target_dbs>
  <queries>
    <motif db="0" id="CACRTGST" alt="MEME-3" length="8" nsites="218" evalue="6.8e-067">
      <pos A="0.000105548" C="0.999665" G="0.000123705" T="0.000105548"/>
      <pos A="0.999647" C="0.000123705" G="0.000123705" T="0.000105548"/>
      <pos A="0.000105548" C="0.999665" G="0.000123705" T="0.000105548"/>
      <pos A="0.481536" C="0.000123705" G="0.518235" T="0.000105548"/>
      <pos A="0.000105548" C="0.000123705" G="0.000123705" T="0.999647"/>
      <pos A="0.000105548" C="0.000123705" G="0.999665" T="0.000105548"/>
      <pos A="0.000105548" C="0.348588" G="0.463214" T="0.188092"/>
      <pos A="0.169753" C="0.215621" G="0.174356" T="0.440271"/>
    </motif>
    <motif db="0" id="GCCACCATGTGGTTGCTGGGAATTG" alt="MEME-2" length="25" nsites="28" evalue="1.1e-141">
      <pos A="0.107581" C="0.000960142" G="0.89064" T="0.000819217"/>
      <pos A="0.0364061" C="0.89064" G="0.036547" T="0.0364061"/>
      <pos A="0.0364061" C="0.819466" G="0.000960142" T="0.143168"/>
      <pos A="0.819325" C="0.000960142" G="0.178896" T="0.000819217"/>
      <pos A="0.000819217" C="0.997401" G="0.000960142" T="0.000819217"/>
      <pos A="0.000819217" C="0.997401" G="0.000960142" T="0.000819217"/>
      <pos A="0.99726" C="0.000960142" G="0.000960142" T="0.000819217"/>
      <pos A="0.000819217" C="0.178896" G="0.000960142" T="0.819325"/>
      <pos A="0.000819217" C="0.000960142" G="0.997401" T="0.000819217"/>
      <pos A="0.000819217" C="0.036547" G="0.000960142" T="0.961674"/>
      <pos A="0.0364061" C="0.000960142" G="0.961815" T="0.000819217"/>
      <pos A="0.000819217" C="0.0721349" G="0.926227" T="0.000819217"/>
      <pos A="0.0364061" C="0.000960142" G="0.178896" T="0.783737"/>
      <pos A="0.000819217" C="0.000960142" G="0.0721349" T="0.926086"/>
      <pos A="0.0364061" C="0.036547" G="0.89064" T="0.0364061"/>
      <pos A="0.0364061" C="0.855053" G="0.036547" T="0.071994"/>
      <pos A="0.0364061" C="0.0721349" G="0.036547" T="0.854912"/>
      <pos A="0.0364061" C="0.000960142" G="0.89064" T="0.071994"/>
      <pos A="0.143168" C="0.000960142" G="0.855053" T="0.000819217"/>
      <pos A="0.0364061" C="0.000960142" G="0.961815" T="0.000819217"/>
      <pos A="0.890499" C="0.000960142" G="0.0721349" T="0.0364061"/>
      <pos A="0.783737" C="0.036547" G="0.0721349" T="0.107581"/>
      <pos A="0.0364061" C="0.143309" G="0.000960142" T="0.819325"/>
      <pos A="0.0364061" C="0.0721349" G="0.000960142" T="0.890499"/>
      <pos A="0.071994" C="0.036547" G="0.748291" T="0.143168"/>
    </motif>
    <motif db="0" id="GGATCTGRYGCCCTCTTCTGGCCT" alt="MEME-1" length="24" nsites="51" evalue="4.0e-210">
      <pos A="0.137437" C="0.0200976" G="0.66589" T="0.176576"/>
      <pos A="0.235284" C="0.000527984" G="0.705029" T="0.0591594"/>
      <pos A="0.74409" C="0.0788055" G="0.117945" T="0.0591594"/>
      <pos A="0.0200201" C="0.0788055" G="0.0592369" T="0.841938"/>
      <pos A="0.078728" C="0.802877" G="0.0592369" T="0.0591594"/>
      <pos A="0.0395897" C="0.196222" G="0.000527984" T="0.76366"/>
      <pos A="0.235284" C="0.000527984" G="0.724598" T="0.0395897"/>
      <pos A="0.548396" C="0.0592369" G="0.29407" T="0.0982976"/>
      <pos A="0.0200201" C="0.431057" G="0.000527984" T="0.548396"/>
      <pos A="0.0591594" C="0.000527984" G="0.881154" T="0.0591594"/>
      <pos A="0.0200201" C="0.959432" G="0.000527984" T="0.0200201"/>
      <pos A="0.000450489" C="0.998571" G="0.000527984" T="0.000450489"/>
      <pos A="0.0200201" C="0.979001" G="0.000527984" T="0.000450489"/>
      <pos A="0.0200201" C="0.0788055" G="0.000527984" T="0.900646"/>
      <pos A="0.000450489" C="0.979001" G="0.000527984" T="0.0200201"/>
      <pos A="0.000450489" C="0.000527984" G="0.000527984" T="0.998494"/>
      <pos A="0.0395897" C="0.0396672" G="0.0983751" T="0.822368"/>
      <pos A="0.000450489" C="0.959432" G="0.0396672" T="0.000450489"/>
      <pos A="0.0200201" C="0.000527984" G="0.000527984" T="0.978924"/>
      <pos A="0.000450489" C="0.000527984" G="0.998571" T="0.000450489"/>
      <pos A="0.0395897" C="0.000527984" G="0.920294" T="0.0395897"/>
      <pos A="0.0591594" C="0.705029" G="0.0396672" T="0.196145"/>
      <pos A="0.254854" C="0.587612" G="0.117945" T="0.0395897"/>
      <pos A="0.176576" C="0.0788055" G="0.0788055" T="0.665813"/>
    </motif>
  </queries>
  <targets>
    <motif db="0" id="BCL6B_DBD" length="17" nsites="20"
        url="http://floresta.eead.csic.es/footprintdb/index.php?db=HumanTF:1.0&amp;motif=BCL6B_DBD">
      <pos A="0.00114527" C="0.084995" G="0.00134229" T="0.912517"/>
      <pos A="0.0168557" C="0.00134229" G="0.975419" T="0.00638209"/>
      <pos A="0.00114527" C="0.990974" G="0.00134229" T="0.00653831"/>
      <pos A="0.00114527" C="0.00134229" G="0.00134229" T="0.99617"/>
      <pos A="0.00114527" C="0.00134229" G="0.00134229" T="0.99617"/>
      <pos A="0.00114527" C="0.00134229" G="0.0106418" T="0.986871"/>
      <pos A="0.00114527" C="0.996367" G="0.00134229" T="0.00114527"/>
      <pos A="0.00114527" C="0.0472667" G="0.131461" T="0.820127"/>
      <pos A="0.99617" C="0.00134229" G="0.00134229" T="0.00114527"/>
      <pos A="0.00114527" C="0.00134229" G="0.996367" T="0.00114527"/>
      <pos A="0.00114527" C="0.00134229" G="0.996367" T="0.00114527"/>
      <pos A="0.989331" C="0.00134229" G="0.00818109" T="0.00114527"/>
      <pos A="0.99617" C="0.00134229" G="0.00134229" T="0.00114527"/>
      <pos A="0.00114527" C="0.0105134" G="0.00134229" T="0.986999"/>
      <pos A="0.00114527" C="0.0714766" G="0.00134229" T="0.926036"/>
      <pos A="0.309194" C="0.663783" G="0.0258776" T="0.00114527"/>
      <pos A="0.543079" C="0.433704" G="0.0220716" T="0.00114527"/>
    </motif>
    <motif db="0" id="BHLHA15_DBD" length="10" nsites="20"
        url="http://floresta.eead.csic.es/footprintdb/index.php?db=HumanTF:1.0&amp;motif=BHLHA15_DBD">
      <pos A="0.682963" C="0.0689065" G="0.140295" T="0.107836"/>
      <pos A="0.248357" C="0.703067" G="0.0470388" T="0.00153731"/>
      <pos A="0.00407662" C="0.99285" G="0.00192836" T="0.00114527"/>
      <pos A="0.986172" C="0.00240995" G="0.0100786" T="0.0013393"/>
      <pos A="0.00114527" C="0.00134229" G="0.00670647" T="0.990806"/>
      <pos A="0.989547" C="0.00796517" G="0.00134229" T="0.00114527"/>
      <pos A="0.00181891" C="0.0197114" G="0.00134229" T="0.977127"/>
      <pos A="0.00114527" C="0.00134229" G="0.99402" T="0.00349254"/>
      <pos A="0.00202786" C="0.12371" G="0.585532" T="0.288729"/>
      <pos A="0.159792" C="0.2349" G="0.0443871" T="0.56092"/>
    </motif>
    <motif db="0" id="CLOCK_DBD" length="10" nsites="20"
        url="http://floresta.eead.csic.es/footprintdb/index.php?db=HumanTF:1.0&amp;motif=CLOCK_DBD">
      <pos A="0.525331" C="0.0825214" G="0.217047" T="0.1751"/>
      <pos A="0.694109" C="0.138643" G="0.145104" T="0.0221443"/>
      <pos A="0.025797" C="0.962751" G="0.00582488" T="0.00562786"/>
      <pos A="0.951849" C="0.0124229" G="0.0345841" T="0.00114527"/>
      <pos A="0.034804" C="0.903807" G="0.00134229" T="0.0600478"/>
      <pos A="0.086009" C="0.00134229" G="0.911503" T="0.00114527"/>
      <pos A="0.00789851" C="0.012598" G="0.012598" T="0.966904"/>
      <pos A="0.00114527" C="0.00811144" G="0.969292" T="0.0214517"/>
      <pos A="0.00258308" C="0.219902" G="0.159511" T="0.618003"/>
      <pos A="0.207093" C="0.297535" G="0.0915891" T="0.403783"/>
    </motif>
    <motif db="0" id="MAX_DBD_1" length="17" nsites="20"
        url="http://floresta.eead.csic.es/footprintdb/index.php?db=HumanTF:1.0&amp;motif=MAX_DBD_1">
      <pos A="0.0186159" C="0.977705" G="0.0017393" T="0.0019393"/>
      <pos A="0.958035" C="0.00562289" G="0.0227453" T="0.013598"/>
      <pos A="0.00304577" C="0.935936" G="0.00590348" T="0.0551154"/>
      <pos A="0.0749333" C="0.00581393" G="0.917734" T="0.00151841"/>
      <pos A="0.0162557" C="0.0519622" G="0.0017204" T="0.930062"/>
      <pos A="0.00393035" C="0.00333134" G="0.979658" T="0.0130806"/>
      <pos A="0.135137" C="0.385102" G="0.292806" T="0.186953"/>
      <pos A="0.223477" C="0.316818" G="0.12567" T="0.334035"/>
      <pos A="0.361573" C="0.309933" G="0.152398" T="0.176095"/>
      <pos A="0.403363" C="0.217019" G="0.218637" T="0.16098"/>
      <pos A="0.321625" C="0.325869" G="0.219447" T="0.13306"/>
      <pos A="0.00994726" C="0.985164" G="0.00294229" T="0.00194527"/>
      <pos A="0.959534" C="0.00329055" G="0.0243373" T="0.0128378"/>
      <pos A="0.00191841" C="0.951542" G="0.00327463" T="0.0432647"/>
      <pos A="0.109207" C="0.00990149" G="0.878319" T="0.00257214"/>
      <pos A="0.0455274" C="0.0675582" G="0.00563781" T="0.881277"/>
      <pos A="0.00272537" C="0.00213234" G="0.972667" T="0.0224756"/>
    </motif>
    <motif db="0" id="MAX_DBD_2" length="10" nsites="20"
        url="http://floresta.eead.csic.es/footprintdb/index.php?db=HumanTF:1.0&amp;motif=MAX_DBD_2">
      <pos A="0.479631" C="0.226478" G="0.188714" T="0.105176"/>
      <pos A="0.278304" C="0.407892" G="0.220465" T="0.0933393"/>
      <pos A="0.00675721" C="0.990755" G="0.00134229" T="0.00114527"/>
      <pos A="0.978404" C="0.00134229" G="0.0137075" T="0.00654627"/>
      <pos A="0.00114527" C="0.963349" G="0.00232139" T="0.0331841"/>
      <pos A="0.0462179" C="0.00668557" G="0.943348" T="0.00374826"/>
      <pos A="0.0107831" C="0.0235502" G="0.00413532" T="0.961531"/>
      <pos A="0.00114527" C="0.00521393" G="0.987333" T="0.00630746"/>
      <pos A="0.19523" C="0.355933" G="0.238412" T="0.210426"/>
      <pos A="0.163509" C="0.323321" G="0.144026" T="0.369142"/>
    </motif>
    <motif db="0" id="MNT_DBD" length="10" nsites="20"
        url="http://floresta.eead.csic.es/footprintdb/index.php?db=HumanTF:1.0&amp;motif=MNT_DBD">
      <pos A="0.408799" C="0.188366" G="0.213205" T="0.18963"/>
      <pos A="0.274375" C="0.334479" G="0.29795" T="0.093196"/>
      <pos A="0.0388249" C="0.951709" G="0.00134229" T="0.00812338"/>
      <pos A="0.966404" C="0.00134229" G="0.00134229" T="0.0309114"/>
      <pos A="0.00114527" C="0.96386" G="0.0112358" T="0.0237592"/>
      <pos A="0.02259" C="0.00134229" G="0.974922" T="0.00114527"/>
      <pos A="0.00114527" C="0.00134229" G="0.0227871" T="0.974725"/>
      <pos A="0.00114527" C="0.00134229" G="0.961132" T="0.0363801"/>
      <pos A="0.219992" C="0.411315" G="0.192469" T="0.176223"/>
      <pos A="0.233123" C="0.335449" G="0.110766" T="0.320662"/>
    </motif>
    <motif db="1" id="MA0004.1" alt="Arnt" length="6" nsites="20"
        url="http://jaspar2018.genereg.net/matrix/MA0004.1">
      <pos A="0.20015" C="0.797362" G="0.00134229" T="0.00114527"/>
      <pos A="0.946419" C="0.00134229" G="0.0510935" T="0.00114527"/>
      <pos A="0.00114527" C="0.996367" G="0.00134229" T="0.00114527"/>
      <pos A="0.00114527" C="0.00134229" G="0.996367" T="0.00114527"/>
      <pos A="0.00114527" C="0.00134229" G="0.00134229" T="0.99617"/>
      <pos A="0.00114527" C="0.00134229" G="0.996367" T="0.00114527"/>
    </motif>
    <motif db="1" id="MA0058.3" alt="MAX" length="10" nsites="6877"
        url="http://jaspar2018.genereg.net/matrix/MA0058.3">
      <pos A="0.480874" C="0.226262" G="0.18831" T="0.104553"/>
      <pos A="0.278544" C="0.40858" G="0.220219" T="0.092657"/>
      <pos A="0.00564327" C="0.994349" G="3.92316e-06" T="3.34734e-06"/>
      <pos A="0.982134" C="3.92316e-06" G="0.0124307" T="0.00543127"/>
      <pos A="3.34734e-06" C="0.966807" G="0.000987909" T="0.0322019"/>
      <pos A="0.0453007" C="0.00537385" G="0.946706" T="0.00261931"/>
      <pos A="0.00968921" C="0.0223226" G="0.00281088" T="0.965177"/>
      <pos A="3.34734e-06" C="0.00389487" G="0.990911" T="0.00519127"/>
      <pos A="0.195056" C="0.356363" G="0.238255" T="0.210327"/>
      <pos A="0.163177" C="0.323588" G="0.143399" T="0.369835"/>
    </motif>
    <motif db="1" id="MA0059.1" alt="MAX::MYC" length="11" nsites="21"
        url="http://jaspar2018.genereg.net/matrix/MA0059.1">
      <pos A="0.332844" C="0.048672" G="0.427819" T="0.190664"/>
      <pos A="0.711992" C="0.048672" G="0.190852" T="0.0484843"/>
      <pos A="0.0958776" C="0.427819" G="0.427819" T="0.0484843"/>
      <pos A="0.0484843" C="0.949146" G="0.00127867" T="0.001091"/>
      <pos A="0.996352" C="0.00127867" G="0.00127867" T="0.001091"/>
      <pos A="0.001091" C="0.949146" G="0.00127867" T="0.0484843"/>
      <pos A="0.0484843" C="0.00127867" G="0.949146" T="0.001091"/>
      <pos A="0.001091" C="0.048672" G="0.00127867" T="0.948958"/>
      <pos A="0.001091" C="0.00127867" G="0.996539" T="0.001091"/>
      <pos A="0.0484843" C="0.048672" G="0.854359" T="0.0484843"/>
      <pos A="0.143271" C="0.238245" G="0.00127867" T="0.617205"/>
    </motif>
    <motif db="1" id="MA0093.2" alt="USF1" length="11" nsites="16842"
        url="http://jaspar2018.genereg.net/matrix/MA0093.2">
      <pos A="0.287733" C="0.223489" G="0.425245" T="0.063533"/>
      <pos A="0.0874018" C="0.442227" G="0.177118" T="0.293255"/>
      <pos A="0.00255435" C="0.997443" G="1.60194e-06" T="1.36681e-06"/>
      <pos A="0.984024" C="1.60194e-06" G="1.60194e-06" T="0.0159733"/>
      <pos A="0.0111643" C="0.610317" G="0.0553393" T="0.323179"/>
      <pos A="0.0952978" C="0.0353294" G="0.86937" T="1.36681e-06"/>
      <pos A="1.36681e-06" C="1.60194e-06" G="1.60194e-06" T="0.999995"/>
      <pos A="1.36681e-06" C="1.60194e-06" G="0.999996" T="1.36681e-06"/>
      <pos A="0.876495" C="1.60194e-06" G="0.0816421" T="0.0418611"/>
      <pos A="1.36681e-06" C="0.781733" G="1.60194e-06" T="0.218264"/>
      <pos A="0.108124" C="0.589358" G="0.0660862" T="0.236433"/>
    </motif>
    <motif db="1" id="MA0104.4" alt="MYCN" length="12" nsites="6984"
        url="http://jaspar2018.genereg.net/matrix/MA0104.4">
      <pos A="0.213058" C="0.271191" G="0.351374" T="0.164377"/>
      <pos A="0.248282" C="0.221937" G="0.372135" T="0.157647"/>
      <pos A="0.0687313" C="0.764741" G="0.106388" T="0.0601394"/>
      <pos A="0.00487123" C="0.992115" G="0.00200883" T="0.00100528"/>
      <pos A="0.911932" C="0.00802175" G="0.0408113" T="0.0392357"/>
      <pos A="0.00315325" C="0.933124" G="0.0174716" T="0.0462516"/>
      <pos A="0.0462516" C="0.0174716" G="0.933124" T="0.00315325"/>
      <pos A="0.0392357" C="0.0408113" G="0.00802175" T="0.911932"/>
      <pos A="0.00100528" C="0.00200883" G="0.992115" T="0.00487123"/>
      <pos A="0.0601394" C="0.106388" G="0.764741" T="0.0687313"/>
      <pos A="0.157647" C="0.372135" G="0.221937" T="0.248282"/>
      <pos A="0.164377" C="0.351374" G="0.271191" T="0.213058"/>
    </motif>
    <motif db="1" id="MA0139.1" alt="CTCF" length="19" nsites="913"
        url="http://jaspar2018.genereg.net/matrix/MA0139.1">
      <pos A="0.0953048" C="0.318724" G="0.0832624" T="0.502708"/>
      <pos A="0.182918" C="0.158829" G="0.45343" T="0.204822"/>
      <pos A="0.307769" C="0.0536927" G="0.491761" T="0.146778"/>
      <pos A="0.0613545" C="0.876166" G="0.023028" T="0.0394509"/>
      <pos A="0.00878625" C="0.988968" G="2.95477e-05" T="0.00221597"/>
      <pos A="0.814832" C="0.014267" G="0.0712158" T="0.0996853"/>
      <pos A="0.0438324" C="0.578279" G="0.365816" T="0.0120719"/>
      <pos A="0.117337" C="0.474759" G="0.0526558" T="0.355249"/>
      <pos A="0.933037" C="0.0120892" G="0.0351137" T="0.01976"/>
      <pos A="0.00551261" C="2.95477e-05" G="0.991139" T="0.00331785"/>
      <pos A="0.365517" C="0.00332219" G="0.621257" T="0.00990313"/>
      <pos A="0.0592947" C="0.0132001" G="0.553207" T="0.374298"/>
      <pos A="0.0132108" C="2.95477e-05" G="0.977944" T="0.00881525"/>
      <pos A="0.0615565" C="0.00881958" G="0.851584" T="0.0780387"/>
      <pos A="0.114424" C="0.806322" G="0.00552995" T="0.0737241"/>
      <pos A="0.409221" C="0.014329" G="0.557724" T="0.0187252"/>
      <pos A="0.0903233" C="0.530808" G="0.338099" T="0.0407697"/>
      <pos A="0.128866" C="0.354617" G="0.0804167" T="0.4361"/>
      <pos A="0.442708" C="0.199347" G="0.292949" T="0.0649961"/>
    </motif>
    <motif db="1" id="MA0147.3" alt="MYC" length="12" nsites="4942"
        url="http://jaspar2018.genereg.net/matrix/MA0147.3">
      <pos A="0.210036" C="0.272157" G="0.33367" T="0.184137"/>
      <pos A="0.206192" C="0.260421" G="0.355522" T="0.177864"/>
      <pos A="0.0886309" C="0.757983" G="0.0955115" T="0.0578745"/>
      <pos A="0.00890748" C="0.979347" G="0.00627833" T="0.00546755"/>
      <pos A="0.930783" C="0.0119432" G="0.0344038" T="0.0228692"/>
      <pos A="0.0109314" C="0.915608" G="0.0141692" T="0.0592915"/>
      <pos A="0.034201" C="0.0317738" G="0.926333" T="0.0076935"/>
      <pos A="0.0119424" C="0.0327848" G="0.0127532" T="0.942519"/>
      <pos A="0.00465856" C="0.0113362" G="0.974693" T="0.00931247"/>
      <pos A="0.0847859" C="0.566769" G="0.242413" T="0.106033"/>
      <pos A="0.194457" C="0.308376" G="0.209633" T="0.287534"/>
      <pos A="0.152774" C="0.361188" G="0.272764" T="0.213274"/>
    </motif>
    <motif db="1" id="MA0617.1" alt="Id2" length="8" nsites="1000"
        url="http://jaspar2018.genereg.net/matrix/MA0617.1">
      <pos A="0.277995" C="0.16701" G="0.498977" T="0.0560174"/>
      <pos A="2.30177e-05" C="0.999927" G="2.69773e-05" T="2.30177e-05"/>
      <pos A="0.999923" C="2.69773e-05" G="2.69773e-05" T="2.30177e-05"/>
      <pos A="2.30177e-05" C="0.999927" G="2.69773e-05" T="2.30177e-05"/>
      <pos A="2.30177e-05" C="2.69773e-05" G="0.999927" T="2.30177e-05"/>
      <pos A="2.30177e-05" C="2.69773e-05" G="2.69773e-05" T="0.999923"/>
      <pos A="2.30177e-05" C="2.69773e-05" G="0.999927" T="2.30177e-05"/>
      <pos A="0.499473" C="0.0459764" G="0.272727" T="0.181823"/>
    </motif>
    <motif db="1" id="MA0626.1" alt="Npas2" length="10" nsites="1000"
        url="http://jaspar2018.genereg.net/matrix/MA0626.1">
      <pos A="0.272996" C="0.177009" G="0.292998" T="0.256997"/>
      <pos A="0.154162" C="0.377366" G="0.420405" T="0.0480662"/>
      <pos A="2.30177e-05" C="0.999927" G="2.69773e-05" T="2.30177e-05"/>
      <pos A="0.999923" C="2.69773e-05" G="2.69773e-05" T="2.30177e-05"/>
      <pos A="0.0810959" C="0.918854" G="2.69773e-05" T="2.30177e-05"/>
      <pos A="0.0810959" C="2.69773e-05" G="0.918854" T="2.30177e-05"/>
      <pos A="2.30177e-05" C="2.69773e-05" G="2.69773e-05" T="0.999923"/>
      <pos A="0.0810959" C="2.69773e-05" G="0.918854" T="2.30177e-05"/>
      <pos A="0.0740156" C="0.17201" G="0.188008" T="0.565966"/>
      <pos A="0.296993" C="0.298997" G="0.202007" T="0.202003"/>
    </motif>
    <motif db="1" id="MA0731.1" alt="BCL6B" length="17" nsites="226"
        url="http://jaspar2018.genereg.net/matrix/MA0731.1">
      <pos A="0.000101813" C="0.0841531" G="0.000119328" T="0.915626"/>
      <pos A="0.0158838" C="0.000119328" G="0.978633" T="0.00536249"/>
      <pos A="0.000101813" C="0.994259" G="0.000119328" T="0.00551942"/>
      <pos A="0.000101813" C="0.000119328" G="0.000119328" T="0.99966"/>
      <pos A="0.000101813" C="0.000119328" G="0.000119328" T="0.99966"/>
      <pos A="0.000101813" C="0.000119328" G="0.00946119" T="0.990318"/>
      <pos A="0.000101813" C="0.999677" G="0.000119328" T="0.000101813"/>
      <pos A="0.000101813" C="0.0462529" G="0.13083" T="0.822815"/>
      <pos A="0.99966" C="0.000119328" G="0.000119328" T="0.000101813"/>
      <pos A="0.000101813" C="0.000119328" G="0.999677" T="0.000101813"/>
      <pos A="0.000101813" C="0.000119328" G="0.999677" T="0.000101813"/>
      <pos A="0.99279" C="0.000119328" G="0.00698929" T="0.000101813"/>
      <pos A="0.99966" C="0.000119328" G="0.000119328" T="0.000101813"/>
      <pos A="0.000101813" C="0.00933225" G="0.000119328" T="0.990447"/>
      <pos A="0.000101813" C="0.0705732" G="0.000119328" T="0.929206"/>
      <pos A="0.309554" C="0.665578" G="0.0247664" T="0.000101813"/>
      <pos A="0.544504" C="0.434451" G="0.0209431" T="0.000101813"/>
    </motif>
    <motif db="1" id="MA0819.1" alt="CLOCK" length="10" nsites="429"
        url="http://jaspar2018.genereg.net/matrix/MA0819.1">
      <pos A="0.526738" C="0.0816289" G="0.216795" T="0.174838"/>
      <pos A="0.69632" C="0.138018" G="0.14451" T="0.0211527"/>
      <pos A="0.0248229" C="0.966054" G="0.00456683" T="0.0045576"/>
      <pos A="0.955288" C="0.0111963" G="0.0334631" T="5.36472e-05"/>
      <pos A="0.0338728" C="0.906829" G="6.28758e-05" T="0.0592369"/>
      <pos A="0.0853218" C="6.28758e-05" G="0.914562" T="5.36472e-05"/>
      <pos A="0.00683907" C="0.0113722" G="0.0113722" T="0.970415"/>
      <pos A="5.36472e-05" C="0.00686429" G="0.972625" T="0.0204569"/>
      <pos A="0.00149831" C="0.219665" G="0.158986" T="0.619851"/>
      <pos A="0.206982" C="0.297668" G="0.0907397" T="0.40461"/>
    </motif>
    <motif db="1" id="MA0825.1" alt="MNT" length="10" nsites="681"
        url="http://jaspar2018.genereg.net/matrix/MA0825.1">
      <pos A="0.409666" C="0.187971" G="0.21293" T="0.189433"/>
      <pos A="0.274589" C="0.334792" G="0.298087" T="0.0925312"/>
      <pos A="0.0378962" C="0.955018" G="3.96124e-05" T="0.00704577"/>
      <pos A="0.969976" C="3.96124e-05" G="3.96124e-05" T="0.0299444"/>
      <pos A="3.37983e-05" C="0.967228" G="0.00998115" T="0.0227575"/>
      <pos A="0.0215826" C="3.96124e-05" G="0.978344" T="3.37983e-05"/>
      <pos A="3.37983e-05" C="3.96124e-05" G="0.0215884" T="0.978338"/>
      <pos A="3.37983e-05" C="3.96124e-05" G="0.964487" T="0.0354396"/>
      <pos A="0.219943" C="0.412002" G="0.192093" T="0.175961"/>
      <pos A="0.233138" C="0.335767" G="0.109994" T="0.321101"/>
    </motif>
    <motif db="1" id="MA1102.1" alt="CTCFL" length="14" nsites="8825"
        url="http://jaspar2018.genereg.net/matrix/MA1102.1">
      <pos A="0.0710498" C="0.783563" G="0.097452" T="0.0479341"/>
      <pos A="0.378922" C="0.1685" G="0.285552" T="0.167026"/>
      <pos A="0.103004" C="0.526909" G="0.328384" T="0.0417021"/>
      <pos A="0.056546" C="0.759541" G="0.0606254" T="0.123287"/>
      <pos A="0.954326" C="0.0188128" G="0.0172269" T="0.0096345"/>
      <pos A="0.00861451" C="0.0105409" G="0.974043" T="0.00680153"/>
      <pos A="0.0643649" C="0.0164339" G="0.910475" T="0.00872751"/>
      <pos A="0.0301443" C="0.0368296" G="0.874327" T="0.0586989"/>
      <pos A="0.0139405" C="0.0202858" G="0.957159" T="0.00861451"/>
      <pos A="0.0143934" C="0.0154139" G="0.949567" T="0.0206254"/>
      <pos A="0.0132605" C="0.977329" G="0.00419601" T="0.00521455"/>
      <pos A="0.455748" C="0.0827221" G="0.419488" T="0.0420421"/>
      <pos A="0.0809087" C="0.42742" G="0.390707" T="0.100964"/>
      <pos A="0.150596" C="0.384362" G="0.2051" T="0.259943"/>
    </motif>
    <motif db="1" id="MA1108.1" alt="MXI1" length="13" nsites="3703"
        url="http://jaspar2018.genereg.net/matrix/MA1108.1">
      <pos A="0.194168" C="0.32595" G="0.311368" T="0.168514"/>
      <pos A="0.220902" C="0.302997" G="0.32838" T="0.14772"/>
      <pos A="0.374017" C="0.223603" G="0.2606" T="0.141779"/>
      <pos A="0.102082" C="0.717784" G="0.131249" T="0.0488839"/>
      <pos A="0.0153988" C="0.961094" G="0.0145899" T="0.00891798"/>
      <pos A="0.953531" C="0.0129689" G="0.0262016" T="0.00729702"/>
      <pos A="0.0043271" C="0.944892" G="0.012159" T="0.0386222"/>
      <pos A="0.0197197" C="0.0156699" G="0.963524" T="0.00108619"/>
      <pos A="0.00540707" C="0.0297125" G="0.00864905" T="0.956232"/>
      <pos A="0.00540707" C="0.0243116" G="0.958663" T="0.0116179"/>
      <pos A="0.0918207" C="0.478525" G="0.299486" T="0.130168"/>
      <pos A="0.181205" C="0.312448" G="0.279503" T="0.226843"/>
      <pos A="0.142859" C="0.359166" G="0.286524" T="0.211451"/>
    </motif>
    <motif db="2" id="UP00060_1" alt="Max_primary" length="16" nsites="20"
        url="http://the_brain.bwh.harvard.edu/uniprobe/details2.php?id=00060">
      <pos A="0.234832" C="0.153122" G="0.301561" T="0.310485"/>
      <pos A="0.19938" C="0.148565" G="0.438407" T="0.213648"/>
      <pos A="0.581171" C="0.274743" G="0.0768308" T="0.0672547"/>
      <pos A="0.139284" C="0.474405" G="0.305704" T="0.080607"/>
      <pos A="0.026" C="0.966209" G="0.00314428" T="0.00464776"/>
      <pos A="0.962683" C="0.00505174" G="0.0235512" T="0.00871443"/>
      <pos A="0.0017403" C="0.903836" G="0.00946169" T="0.0849622"/>
      <pos A="0.0849622" C="0.00946169" G="0.903836" T="0.0017403"/>
      <pos A="0.00871443" C="0.0235512" G="0.00505174" T="0.962683"/>
      <pos A="0.00464776" C="0.00314428" G="0.966209" T="0.026"/>
      <pos A="0.149543" C="0.24136" G="0.389002" T="0.220095"/>
      <pos A="0.0672547" C="0.0768308" G="0.274743" T="0.581171"/>
      <pos A="0.187205" C="0.345819" G="0.250164" T="0.216812"/>
      <pos A="0.273222" C="0.226107" G="0.300584" T="0.200087"/>
      <pos A="0.161238" C="0.111966" G="0.476927" T="0.24987"/>
      <pos A="0.172081" C="0.102095" G="0.42381" T="0.302016"/>
    </motif>
  </targets>
  <matches>
    <query idx="2">
      <target idx="11" rc="y" off="-5" pv="8.33e-06" ev="1.51e-02" qv="3.00e-02"/>
      <target idx="18" rc="y" off="-6" pv="3.90e-04" ev="7.05e-01" qv="6.98e-01"/>
    </query>
    <query idx="1">
      <target idx="1" rc="y" off="-3" pv="2.27e-04" ev="4.10e-01" qv="3.03e-01"/>
      <target idx="8" rc="y" off="-3" pv="2.44e-04" ev="4.41e-01" qv="3.03e-01"/>
      <target idx="0" rc="n" off="-9" pv="4.71e-04" ev="8.51e-01" qv="3.03e-01"/>
      <target idx="15" rc="n" off="-9" pv="4.71e-04" ev="8.51e-01" qv="3.03e-01"/>
    </query>
    <query idx="0">
      <target idx="5" rc="y" off="2" pv="1.62e-06" ev="2.93e-03" qv="1.98e-03"/>
      <target idx="17" rc="y" off="2" pv="1.62e-06" ev="2.93e-03" qv="1.98e-03"/>
      <target idx="8" rc="y" off="2" pv="1.71e-06" ev="3.09e-03" qv="1.98e-03"/>
      <target idx="4" rc="y" off="2" pv="4.32e-06" ev="7.82e-03" qv="3.00e-03"/>
      <target idx="7" rc="y" off="2" pv="4.32e-06" ev="7.82e-03" qv="3.00e-03"/>
      <target idx="20" rc="y" off="6" pv="7.43e-06" ev="1.34e-02" qv="4.29e-03"/>
      <target idx="19" rc="y" off="3" pv="1.91e-05" ev="3.46e-02" qv="7.37e-03"/>
      <target idx="3" rc="y" off="0" pv="3.19e-05" ev="5.77e-02" qv="1.10e-02"/>
      <target idx="14" rc="y" off="2" pv="6.89e-05" ev="1.24e-01" qv="1.83e-02"/>
      <target idx="6" rc="n" off="0" pv="8.68e-05" ev="1.57e-01" qv="1.92e-02"/>
      <target idx="2" rc="n" off="2" pv="1.63e-04" ev="2.95e-01" qv="2.87e-02"/>
      <target idx="16" rc="n" off="2" pv="1.63e-04" ev="2.95e-01" qv="2.87e-02"/>
      <target idx="12" rc="n" off="3" pv="1.69e-04" ev="3.06e-01" qv="2.87e-02"/>
      <target idx="9" rc="y" off="3" pv="2.46e-04" ev="4.45e-01" qv="3.88e-02"/>
      <target idx="10" rc="n" off="3" pv="3.47e-04" ev="6.27e-01" qv="4.62e-02"/>
      <target idx="13" rc="y" off="1" pv="4.70e-04" ev="8.50e-01" qv="6.03e-02"/>
    </query>
  </matches>
  <runtime cycles="65132000" seconds="65.132"/>
</tomtom>
